cici/__init__.py
cici/__main__.py
cici/_version.py
cici/constants.py
cici/exceptions.py
cici/main.py
cici/paths.py
cici/py.typed
cici/utils.py
cici/cli/__init__.py
cici/cli/bundle.py
cici/cli/readme.py
cici/cli/schema.py
cici/cli/update.py
cici/config/__init__.py
cici/config/user.py
cici/config/project/__init__.py
cici/config/project/models.py
cici/config/project/serializers.py
cici/providers/__init__.py
cici/providers/gitlab/__init__.py
cici/providers/gitlab/constants.py
cici/providers/gitlab/models.py
cici/providers/gitlab/normalizers.py
cici/providers/gitlab/serializers.py
cici/providers/gitlab/utils.py
cici/providers/gitlab/yaml_style.py
cici/schema/LICENSE.gitlab
cici/schema/__init__.py
cici/schema/gitlab-ci.json
cici/templates/README.md.j2
cici/templates/__init__.py
cici/templates/brief.md.j2
cici/templates/description.md.j2
cici/templates/group-list.j2
cici/templates/groups.md.j2
cici/templates/target-list.md.j2
cici/templates/target-table.md.j2
cici/templates/targets.md.j2
cici/templates/variable-list.md.j2
cici/templates/variables.md.j2
cici_tools-0.16.1.dist-info/licenses/LICENSE
cici_tools-0.16.1.dist-info/licenses/NOTICE
cici_tools-0.16.1.dist-info/METADATA
cici_tools-0.16.1.dist-info/WHEEL
cici_tools-0.16.1.dist-info/entry_points.txt
cici_tools-0.16.1.dist-info/top_level.txt
cici_tools-0.16.1.dist-info/RECORD
