Metadata-Version: 2.4
Name: cici-tools
Version: 0.16.1
Summary: Continuous Integration Catalog Interface
Author-email: Digital Safety Research Institute <contact@dsri.org>
License: Apache-2.0
Project-URL: Home, https://gitlab.com/saferatday0/cici
Project-URL: Issues, https://gitlab.com/saferatday0/cici/-/issues
Keywords: ci,pipeline,python
Classifier: Development Status :: 1 - Planning
Classifier: Intended Audience :: Developers
Classifier: Topic :: Software Development :: Build Tools
Classifier: License :: OSI Approved :: Apache Software License
Classifier: Programming Language :: Python :: 3
Classifier: Programming Language :: Python :: 3.9
Classifier: Programming Language :: Python :: 3.10
Classifier: Programming Language :: Python :: 3.11
Classifier: Programming Language :: Python :: 3.12
Requires-Python: >=3.9
License-File: LICENSE
License-File: NOTICE
Requires-Dist: appdirs
Requires-Dist: jinja2
Requires-Dist: jsonschema
Requires-Dist: markdown
Requires-Dist: msgspec
Requires-Dist: python-decouple
Requires-Dist: ruamel.yaml
Requires-Dist: termcolor
Dynamic: license-file
